{"data":[{"text":"RT @ShannonAClark8: City Hall Selfie from Christchurch NZ! You can take the kid out of local government but hell they’ll still find a way t…","referenced_tweets":[{"type":"retweeted","id":"1584722868302381057"}],"source":"Twitter Web App","public_metrics":{"retweet_count":1,"reply_count":0,"like_count":0,"quote_count":0},"edit_history_tweet_ids":["1584876162639011841"],"created_at":"2022-10-25T11:54:57.000Z","id":"1584876162639011841","author_id":"319320598"},{"text":"Holy cow. @seoul_metro #CityHallSelfie. Mind blowing city hall. https://t.co/Blin6IG2Of","source":"Twitter for iPhone","public_metrics":{"retweet_count":0,"reply_count":0,"like_count":1,"quote_count":0},"edit_history_tweet_ids":["1584808267339149312"],"created_at":"2022-10-25T07:25:09.000Z","id":"1584808267339149312","author_id":"14072873","attachments":{"media_keys":["3_1584808257314357248"]}},{"text":"City Hall Selfie from Christchurch NZ! You can take the kid out of local government but hell they’ll still find a way to convince their wife to take a picture on vacation! @ELGL50 #cityhallselfie https://t.co/avYBVrKyly","source":"Twitter for iPhone","public_metrics":{"retweet_count":1,"reply_count":1,"like_count":18,"quote_count":0},"edit_history_tweet_ids":["1584722868302381057"],"created_at":"2022-10-25T01:45:49.000Z","id":"1584722868302381057","author_id":"819638891816710144","attachments":{"media_keys":["3_1584722860383563776"]}}],"includes":{"users":[{"username":"ELGL50","description":"We engage the brightest minds in Local Government 🎧 @GovLovePodcast 📷 #CityHallSelfie 🤝 #ELGL22","entities":{"url":{"urls":[{"start":0,"end":23,"url":"https://t.co/H5dflEZsrO","expanded_url":"https://elgl.org/membership/","display_url":"elgl.org/membership/"}]},"description":{"hashtags":[{"start":70,"end":85,"tag":"CityHallSelfie"},{"start":88,"end":95,"tag":"ELGL22"}],"mentions":[{"start":52,"end":67,"username":"GovLovePodcast"}]}},"created_at":"2011-06-17T22:46:59.000Z","verified":false,"location":"Pawnee, Indiana","profile_image_url":"https://pbs.twimg.com/profile_images/1534622639628726272/FPpST0zr_normal.jpg","id":"319320598","name":"ELGL","public_metrics":{"followers_count":13081,"following_count":3275,"tweet_count":58002,"listed_count":355},"url":"https://t.co/H5dflEZsrO","protected":false},{"username":"neilhsimon","description":"Lover of words. Creator of films. Keeping faith in journalism, govt and tech for good. Alum @Tektronix @OregonMetro @oscepa @HelsinkiComm @Gartner_inc","entities":{"description":{"mentions":[{"start":92,"end":102,"username":"Tektronix"},{"start":103,"end":115,"username":"OregonMetro"},{"start":116,"end":123,"username":"oscepa"},{"start":124,"end":137,"username":"HelsinkiComm"},{"start":138,"end":150,"username":"Gartner_inc"}]}},"created_at":"2008-03-03T15:08:03.000Z","verified":false,"location":"Portland, Oregon","profile_image_url":"https://pbs.twimg.com/profile_images/1351625318969139203/J9CDMBoi_normal.jpg","id":"14072873","name":"Neil Simon","public_metrics":{"followers_count":547,"following_count":1151,"tweet_count":3082,"listed_count":14},"protected":false},{"username":"ShannonAClark8","description":"Succesful Campaign Hack/Local Gov Wonk/Proud Non Binary Queer Advocate/Tweets are my own","created_at":"2017-01-12T20:15:14.000Z","verified":false,"profile_image_url":"https://pbs.twimg.com/profile_images/819647689889452032/EPszoXVz_normal.jpg","id":"819638891816710144","name":"Shannon (They/them/theirs)","public_metrics":{"followers_count":152,"following_count":255,"tweet_count":1105,"listed_count":3},"protected":false}],"tweets":[{"text":"City Hall Selfie from Christchurch NZ! You can take the kid out of local government but hell they’ll still find a way to convince their wife to take a picture on vacation! @ELGL50 #cityhallselfie https://t.co/avYBVrKyly","source":"Twitter for iPhone","public_metrics":{"retweet_count":1,"reply_count":1,"like_count":18,"quote_count":0},"edit_history_tweet_ids":["1584722868302381057"],"created_at":"2022-10-25T01:45:49.000Z","id":"1584722868302381057","author_id":"819638891816710144","attachments":{"media_keys":["3_1584722860383563776"]}}],"media":[{"media_key":"3_1584808257314357248","type":"photo"},{"media_key":"3_1584722860383563776","type":"photo"}]},"meta":{"newest_id":"1584876162639011841","oldest_id":"1584722868302381057","result_count":3}}