{"data":[{"author_id":"167446448","text":"Conference run. #UAA2023 #cityhallselfie https://t.co/cBGV9dcgXY","public_metrics":{"retweet_count":0,"reply_count":0,"like_count":9,"quote_count":0,"impression_count":195},"attachments":{"media_keys":["3_1652022768513237020"]},"id":"1652022771084345374","created_at":"2023-04-28T18:51:36.000Z","edit_history_tweet_ids":["1652022771084345374"]}],"includes":{"media":[{"media_key":"3_1652022768513237020","type":"photo"}],"users":[{"description":"This twitter supports Dr. Hersey's Political Science and Public Administration courses at the Uni. of LA - Monroe. Tweets are my own.","id":"167446448","entities":{"url":{"urls":[{"start":0,"end":23,"url":"https://t.co/0W127vQCA5","expanded_url":"http://www.ulm.edu/pols/","display_url":"ulm.edu/pols/"}]}},"verified":false,"protected":false,"public_metrics":{"followers_count":768,"following_count":2049,"tweet_count":5342,"listed_count":5},"url":"https://t.co/0W127vQCA5","location":"Monroe, LA","created_at":"2010-07-16T16:24:02.000Z","name":"ULMHersey","username":"ULMHersey","profile_image_url":"https://pbs.twimg.com/profile_images/768526888323002369/r88b0wos_normal.jpg"}]},"meta":{"newest_id":"1652022771084345374","oldest_id":"1652022771084345374","result_count":1}}