{"data":[{"author_id":"1276583149976371201","source":"Twitter for Android","text":"#CityHallSelfie\n#CityofCulloden\n@ELGL50 https://t.co/TWpYRQCXkv","created_at":"2021-09-21T14:00:00.000Z","public_metrics":{"retweet_count":0,"reply_count":0,"like_count":0,"quote_count":0},"id":"1440314876346257418","attachments":{"media_keys":["3_1440314857543254029"]}},{"author_id":"931237146","source":"Twitter for Android","text":"City Hall front office crew can't wait to get onto the #BicentennialBridge! #CityHallSelfie #SelfiewiththeMayor #JCMO https://t.co/VQik5GAdkV","created_at":"2021-09-16T05:09:02.000Z","public_metrics":{"retweet_count":0,"reply_count":0,"like_count":0,"quote_count":0},"id":"1438369313895985158","attachments":{"media_keys":["3_1438369311274508294"]}},{"author_id":"16426842","source":"Twitter Web App","text":"Not my best work, but being part of the @CityofTLH Neighborhood Leadership Academy will give me lots of chances to practice my #CityHallSelfie skills for next year's @ELGL50 event!\n\nOne session in and already reminded of all the reasons to be #TallahasseeProud.\n\n#Tweet100\n16/100 https://t.co/sjLg3WSHHK","created_at":"2021-09-15T10:50:23.000Z","public_metrics":{"retweet_count":0,"reply_count":0,"like_count":2,"quote_count":0},"id":"1438092827834073089","attachments":{"media_keys":["3_1438092716106207233"]}}],"includes":{"media":[{"media_key":"3_1440314857543254029","type":"photo"},{"media_key":"3_1438369311274508294","type":"photo"},{"media_key":"3_1438092716106207233","type":"photo"}],"users":[{"id":"1276583149976371201","url":"","description":"","created_at":"2020-06-26T18:28:54.000Z","public_metrics":{"followers_count":376,"following_count":0,"tweet_count":34,"listed_count":0},"name":"m","protected":false,"profile_image_url":"https://pbs.twimg.com/profile_images/1429088041998684169/1-pXOefK_normal.jpg","verified":false,"username":"Dennis5833854"},{"id":"931237146","url":"","entities":{"description":{"hashtags":[{"start":62,"end":76,"tag":"MissouriState"},{"start":77,"end":89,"tag":"MayorTergin"},{"start":90,"end":109,"tag":"SelfiewiththeMayor"},{"start":110,"end":121,"tag":"JeffCityMO"},{"start":122,"end":127,"tag":"JCMO"},{"start":128,"end":144,"tag":"CityofJefferson"}],"mentions":[{"start":0,"end":16,"username":"CarriesHallmark"},{"start":41,"end":55,"username":"MissouriState"}]}},"description":"@CarriesHallmark Mayor of Jefferson City @MissouriState Bear! #MissouriState #MayorTergin #SelfiewiththeMayor #JeffCityMO #JCMO #CityofJefferson","created_at":"2012-11-07T04:52:02.000Z","public_metrics":{"followers_count":3890,"following_count":2878,"tweet_count":11174,"listed_count":44},"name":"Carrie Tergin","protected":false,"profile_image_url":"https://pbs.twimg.com/profile_images/378800000004196830/3ceb406e2aa0fb5567147007658c8280_normal.jpeg","verified":false,"username":"CarrieTergin"},{"id":"16426842","url":"https://t.co/CfXh2pCxaw","entities":{"url":{"urls":[{"start":0,"end":23,"url":"https://t.co/CfXh2pCxaw","expanded_url":"http://www.biggreenpen.com","display_url":"biggreenpen.com"}]},"description":{"urls":[{"start":115,"end":138,"url":"https://t.co/MSg9q8jxAq","expanded_url":"https://www.smartbrief.com/author/paula-kiger","display_url":"smartbrief.com/author/paula-k…"}],"hashtags":[{"start":79,"end":90,"tag":"NASASocial"},{"start":93,"end":113,"tag":"WriteOptimistically"}]}},"description":"Wife of one, Mom of two, Friend of many\nNonprofit sector editor at SmartBrief \n#NASASocial  \n#WriteOptimistically \nhttps://t.co/MSg9q8jxAq","created_at":"2008-09-23T22:55:45.000Z","location":"Tallahassee, FL","public_metrics":{"followers_count":12129,"following_count":13342,"tweet_count":162632,"listed_count":459},"name":"Paula Kiger (She/Her)","protected":false,"profile_image_url":"https://pbs.twimg.com/profile_images/1325279118494224384/lplGYyqw_normal.jpg","verified":false,"username":"biggreenpen","pinned_tweet_id":"1439918168831631361"}]},"meta":{"newest_id":"1440314876346257418","oldest_id":"1438092827834073089","result_count":3}}